aussieaddress/__init__.py
aussieaddress/compare.py
aussieaddress-0.1.0.dist-info/LICENSE
aussieaddress-0.1.0.dist-info/METADATA
aussieaddress-0.1.0.dist-info/WHEEL
aussieaddress-0.1.0.dist-info/RECORD
