Metadata-Version: 2.1
Name: aussieaddress
Version: 0.1.0
Summary: Address Matching for Australian Addresses. Compare Address A to Address B and receive a boolean of match and threshold score
License: BSD 3-Clause License
Author: Jack Jorgensen
Author-email: jorgensen.jack@gmail.com
Requires-Python: >=3.7,<4.0
Classifier: License :: Other/Proprietary License
Classifier: Programming Language :: Python :: 3
Classifier: Programming Language :: Python :: 3.7
Classifier: Programming Language :: Python :: 3.8
Classifier: Programming Language :: Python :: 3.9
Classifier: Programming Language :: Python :: 3.10
Classifier: Programming Language :: Python :: 3.11
Requires-Dist: fuzzywuzzy (>=0.18.0,<0.19.0)
Requires-Dist: python-levenshtein (>=0.23.0,<0.24.0)
